LICENSE
MANIFEST.in
README.md
pyproject.toml
setup.cfg
setup.py
rfi_downloader/__init__.py
rfi_downloader/__main__.py
rfi_downloader/application.py
rfi_downloader/applicationwindow.py
rfi_downloader/downloadmanager.py
rfi_downloader/urllistboxrow.py
rfi_downloader/urlobject.py
rfi_downloader/version.py
rfi_downloader.egg-info/PKG-INFO
rfi_downloader.egg-info/SOURCES.txt
rfi_downloader.egg-info/dependency_links.txt
rfi_downloader.egg-info/entry_points.txt
rfi_downloader.egg-info/not-zip-safe
rfi_downloader.egg-info/requires.txt
rfi_downloader.egg-info/top_level.txt
rfi_downloader/data/RFI-logo-transparent.png
rfi_downloader/data/__init__.py
rfi_downloader/data/menus-common.ui
rfi_downloader/utils/__init__.py
rfi_downloader/utils/exceptions.py
rfi_downloader/utils/googleanalytics.py