Metadata-Version: 2.1
Name: rfi-downloader
Version: 0.1.0
Summary: Batch downloader with Gtk GUI
Home-page: https://github.com/RosalindFranklinInstitute/rfi-downloader
Author: Tom Schoonjans
Author-email: Tom.Schoonjans@rfi.ac.uk
License: BSD 3-Clause License
Project-URL: GitHub, https://github.com/RosalindFranklinInstitute/rfi-downloader
Project-URL: Bug-Tracker, https://github.com/RosalindFranklinInstitute/rfi-downloader/issues
Platform: UNKNOWN
Classifier: Development Status :: 3 - Alpha
Classifier: License :: OSI Approved :: BSD License
Classifier: Natural Language :: English
Classifier: Operating System :: POSIX :: Linux
Classifier: Operating System :: Microsoft
Classifier: Operating System :: MacOS :: MacOS X
Classifier: Programming Language :: Python :: 3.8
Requires-Python: >=3.8
License-File: LICENSE
